ntorch/__init__.py
ntorch/config.py
ntorch/data.py
ntorch/gan.py
ntorch/layers.py
ntorch/model.py
ntorch/rl.py
ntorch/trainer.py
ntorch/utils.py
ntorch-1.0.0.dist-info/licenses/LICENSE
ntorch-1.0.0.dist-info/METADATA
ntorch-1.0.0.dist-info/WHEEL
ntorch-1.0.0.dist-info/top_level.txt
ntorch-1.0.0.dist-info/RECORD
