Metadata-Version: 2.4
Name: ntorch
Version: 1.0.0
Summary: A simple PyTorch framework for quick neural network prototyping
Home-page: https://github.com/safe049/ntorch 
Author: safe049
Author-email: safe049@163.com
Classifier: Programming Language :: Python :: 3
Classifier: License :: OSI Approved :: MIT License
Classifier: Operating System :: OS Independent
Requires-Python: >=3.8
License-File: LICENSE
Requires-Dist: torch>=2.0.0
Requires-Dist: torchvision>=0.15.0
Requires-Dist: matplotlib>=3.7.0
Requires-Dist: gym>=0.26.0
Dynamic: author
Dynamic: author-email
Dynamic: classifier
Dynamic: description
Dynamic: description-content-type
Dynamic: home-page
Dynamic: license-file
Dynamic: requires-dist
Dynamic: requires-python
Dynamic: summary
